MANIFEST.in
README.md
setup.py
Moustache.egg-info/PKG-INFO
Moustache.egg-info/SOURCES.txt
Moustache.egg-info/dependency_links.txt
Moustache.egg-info/entry_points.txt
Moustache.egg-info/requires.txt
Moustache.egg-info/top_level.txt
moustache/FusionHelper.py
moustache/InvalidUsage.py
moustache/__init__.py
moustache/wssecretary.py
moustache/images/working.jpg
moustache/templates/test_form.html