Metadata-Version: 1.2
Name: Moustache
Version: 0.2.0
Summary: Module Moustache pour fusion ODT
Home-page: https://gitlab.libriciel.fr/libriciel/hackathon-2018-01/moustache
Author: Libriciel SCOP
Author-email: hackathon@libriciel.coop
License: CeCILL v2
Platform: UNKNOWN
Requires-Python: >=3
